GPTHumanizer/GPTHumanizer.py
GPTHumanizer/__init__.py
gpt_humanizer-0.0.6.dist-info/METADATA
gpt_humanizer-0.0.6.dist-info/WHEEL
gpt_humanizer-0.0.6.dist-info/top_level.txt
gpt_humanizer-0.0.6.dist-info/RECORD
